question_score/__init__.py
question_score/kda.py
question_score/model.py
question_score-0.0.8.dist-info/licenses/LICENSE
question_score-0.0.8.dist-info/METADATA
question_score-0.0.8.dist-info/WHEEL
question_score-0.0.8.dist-info/top_level.txt
question_score-0.0.8.dist-info/RECORD
