Metadata-Version: 2.4
Name: question_score
Version: 0.0.8
Summary: library for question evaluation including KDA, Knowledge Dependent Answerability introduced in EMNLP 2022 work.
Home-page: https://github.com/riiid/question-score
Author: Riiid NLP team
Author-email: ai_nlp@riiid.co
License: Creative Commons Attribution-NonCommercial-ShareAlike 4.0. https://creativecommons.org/licenses/by-nc-sa/4.0/
Classifier: Programming Language :: Python :: 3
Requires-Python: >=3.6
License-File: LICENSE
Requires-Dist: transformers
Requires-Dist: sentencepiece
Requires-Dist: pytorch-lightning
Dynamic: author
Dynamic: author-email
Dynamic: classifier
Dynamic: description
Dynamic: description-content-type
Dynamic: home-page
Dynamic: license
Dynamic: license-file
Dynamic: requires-dist
Dynamic: requires-python
Dynamic: summary
